LICENSE
README.md
setup.cfg
setup.py
AlpacaLumnisTrader/AlpacaLumnisTrader.py
AlpacaLumnisTrader/KEYS.py
AlpacaLumnisTrader/__init__.py
AlpacaLumnisTrader/main.py
AlpacaLumnisTrader/utils.py
alpaca_lumnis_trader.egg-info/PKG-INFO
alpaca_lumnis_trader.egg-info/SOURCES.txt
alpaca_lumnis_trader.egg-info/dependency_links.txt
alpaca_lumnis_trader.egg-info/requires.txt
alpaca_lumnis_trader.egg-info/top_level.txt