Metadata-Version: 2.1
Name: alpaca-lumnis-trader
Version: 0.0.4
Summary: Lumnis Alternative Data
Home-page: https://github.com/lumnisfactors/AlpacaLumnisTrader/archive/refs/tags/0.0.4.tar.gz
Author: Abubakarr Jaye
Author-email: contact@lumnis.io
Classifier: Programming Language :: Python :: 3
Classifier: License :: OSI Approved :: MIT License
Classifier: Operating System :: OS Independent
Requires-Python: >=3.6
License-File: LICENSE
